CHANGES.txt
MANIFEST.in
README.txt
buildout.cfg
minitage.cfg
setup.cfg
setup.py
src/minitage/__init__.py
src/minitage.recipe.scripts.egg-info/PKG-INFO
src/minitage.recipe.scripts.egg-info/SOURCES.txt
src/minitage.recipe.scripts.egg-info/dependency_links.txt
src/minitage.recipe.scripts.egg-info/entry_points.txt
src/minitage.recipe.scripts.egg-info/namespace_packages.txt
src/minitage.recipe.scripts.egg-info/not-zip-safe
src/minitage.recipe.scripts.egg-info/requires.txt
src/minitage.recipe.scripts.egg-info/top_level.txt
src/minitage/recipe/__init__.py
src/minitage/recipe/scripts/__init__.py
src/minitage/recipe/scripts/scripts.py
src/minitage/recipe/scripts/tests/__init__.py
src/minitage/recipe/scripts/tests/arguments.txt
src/minitage/recipe/scripts/tests/env.txt
src/minitage/recipe/scripts/tests/ep.txt
src/minitage/recipe/scripts/tests/generation.txt
src/minitage/recipe/scripts/tests/initialization.txt
src/minitage/recipe/scripts/tests/pi.txt
src/minitage/recipe/scripts/tests/scripts.txt
src/minitage/recipe/scripts/tests/selection.txt
src/minitage/recipe/scripts/tests/tests.py